{"O365Mail.My_Workspace_Microsoft_Outlook_365":{"Resource":"Connection","Key":"5d4f1879-227b-4216-9b56-7730ba245830","Description":null,"Value":{"ConnectionId":{"DefaultValue":"5d4f1879-227b-4216-9b56-7730ba245830","IsExpression":false,"DisplayName":"Connection","Description":"The connection to be used"}},"Metadata":{"Connector":"uipath-microsoft-outlook365","ConnectionType":"O365Mail","BindingsVersion":"2.1"}},"Gmail.My_Workspace_mrvnalexandr_gmail_com":{"Resource":"Connection","Key":"4f5a70f0-c2c4-474a-b1ad-a76b0b341905","Description":null,"Value":{"ConnectionId":{"DefaultValue":"4f5a70f0-c2c4-474a-b1ad-a76b0b341905","IsExpression":false,"DisplayName":"Connection","Description":"The connection to be used"}},"Metadata":{"Connector":"uipath-google-gmail","ConnectionType":"Gmail","BindingsVersion":"2.1"}}}